.gitignore
LICENSE
MANIFEST.in
README.md
requirements.txt
setup.py
tests.py
docs/espace-dev-ird.png
docs/logo.png
docs/logo_name.png
fototex/__init__.py
fototex/_numba.py
fototex/_tools.py
fototex/base.py
fototex/exceptions.py
fototex/foto.py
fototex/foto_tools.py
fototex/io.py
fototex/plotting.py
fototex/utils.py
fototex.egg-info/PKG-INFO
fototex.egg-info/SOURCES.txt
fototex.egg-info/dependency_links.txt
fototex.egg-info/not-zip-safe
fototex.egg-info/requires.txt
fototex.egg-info/top_level.txt