Metadata-Version: 2.1
Name: fototex
Version: 1.5.6
Summary: Fourier Transform Textural Ordination
Home-page: https://framagit.org/benjaminpillot/fototex
Author: Benjamin Pillot <benjamin.pillot@ird.fr>, Dominique Lyszczarz <observatoire@causses-et-cevennes.fr>, Claire Teillet, <teillet.claire@hotmail.com>, Pierre Couteron <pierre.couteron@ird.fr>, Nicolas Barbier <nicolas.barbier@ird.fr>, Philippe Verley <philippe.verley@ird.fr>, Marc Lang <marc.lang@irstea.fr>, Thibault Catry <thibault.catry@ird.fr>, Laurent Demagistri <laurent.demagistri@ird.fr>, Nadine Dessay <nadine.dessay@ird.fr>
License: The MIT Licence
Platform: UNKNOWN
Requires-Python: >=3
